math_tols/__init__.py
math_tols-2.1.8.dist-info/METADATA
math_tols-2.1.8.dist-info/WHEEL
math_tols-2.1.8.dist-info/top_level.txt
math_tols-2.1.8.dist-info/RECORD
