Metadata-Version: 2.4
Name: math_tols
Version: 2.1.8
Summary: Ultimate full math tools library
Author: Abolfazl nb
Classifier: Programming Language :: Python :: 3
Classifier: Operating System :: OS Independent
Classifier: License :: OSI Approved :: MIT License
Requires-Python: >=3.7
Dynamic: author
Dynamic: classifier
Dynamic: description
Dynamic: description-content-type
Dynamic: requires-python
Dynamic: summary
